{"code":{"id":54,"name":"Code des ports maritimes","modified":"2013-01-01T07:00:00.000Z","sections":{"names":["Partie législative","Partie réglementaire - Décrets en Conseil d'Etat"],"sections":{"names":["Livre Ier : Création, organisation et aménagement des ports maritimes civils relevant de la compétence de l'Etat.","Livre II : Droits de port et de navigation.","Livre III : Police des ports maritimes.","Livre IV : Voies ferrées portuaires.","Livre V : Régime du travail dans les ports maritimes.","Livre VI : Création, organisation et aménagement des ports maritimes relevant de la compétence des collectivités territoriales et de leurs groupements."],"sections":{"names":["Titre Ier : Aménagement et exploitation des ports maritimes.","Titre II : Conseils portuaires.","Titre III : Domaine public portuaire."],"sections":{"names":["Chapitre unique."]}}}}}}