{"code":{"id":7,"name":"Code de commerce","modified":"2013-10-13T06:00:00.000Z","sections":{"names":["Partie législative","Partie réglementaire","Annexes de la partie réglementaire","Partie Arrêtés"],"sections":{"names":["LIVRE Ier : Du commerce en général.","LIVRE II : Des sociétés commerciales et des groupements d'intérêt économique.","LIVRE III : De certaines formes de ventes et des clauses d'exclusivité.","LIVRE IV : De la liberté des prix et de la concurrence.","LIVRE V : Des effets de commerce et des garanties.","LIVRE VI : Des difficultés des entreprises.","LIVRE VII : Des juridictions commerciales et de l'organisation du commerce.","LIVRE VIII : De quelques professions réglementées."],"sections":{"names":["TITRE Ier : Des administrateurs judiciaires, des mandataires judiciaires et des experts en diagnostic d'entreprise.","TITRE II : Des commissaires aux comptes.","Annexes partie A Livre VIII"],"sections":{"names":["ANNEXE 8-1\r\n\r\n(ANNEXE À L'ARTICLE A. 811-1)\r\n\r\n","ANNEXE 8-2 (ANNEXE À L'ARTICLE A. 814-1)\n","ANNEXE 8-3 (ANNEXE À L'ARTICLE A. 814-2)","ANNEXE 8-4 (ANNEXE À L'ARTICLE A. 814-3)\n","ANNEXE 8-5 (ANNEXE À L'ARTICLE A. 814-4)\n","ANNEXE 8-7 (ANNEXE À L'ARTICLE A. 822-6)\n","ANNEXE 8-8 (ANNEXE À L'ARTICLE A. 822-29)\n","ANNEXE 8-9 (ANNEXE À L'ARTICLE A. 823-37)","ANNEXE 8-9 (ANNEXE À L'ARTICLE A. 822-1-1)"]}}}}}}